diffusions/__init__.py
diffusions/losses/__init__.py
diffusions/losses/focal_frequency.py
diffusions/lr_schedulers/__init__.py
diffusions/lr_schedulers/cosine_annealing.py
diffusions/models/__init__.py
diffusions/models/activation.py
diffusions/models/attention.py
diffusions/models/blocks.py
diffusions/models/embeddings.py
diffusions/models/imagen/__init__.py
diffusions/models/imagen/blocks.py
diffusions/models/imagen/imagen.py
diffusions/models/imagen/resnet.py
diffusions/models/imagen/unet.py
diffusions/models/resnet.py
diffusions/models/unet.py
diffusions/pipelines/__init__.py
diffusions/pipelines/ddim.py
diffusions/pipelines/ddpm.py
diffusions/schedulers/__init__.py
diffusions/schedulers/ddim.py
diffusions/schedulers/ddpm.py
diffusions/schedulers/scheduler.py
diffusions/utils/__init__.py
diffusions/utils/ema.py
diffusions/utils/jax.py
diffusions/utils/super_resolution.py
diffusions-0.1.13.dist-info/LICENSE
diffusions-0.1.13.dist-info/WHEEL
diffusions-0.1.13.dist-info/METADATA
diffusions-0.1.13.dist-info/RECORD
